CONTRIBUTING.md
MANIFEST.in
README.rst
setup.cfg
setup.py
github_release_notifier/__init__.py
github_release_notifier/cli.py
github_release_notifier/notifier.py
github_release_notifier/parser.py
github_release_notifier/webhook.py
github_release_notifier.egg-info/PKG-INFO
github_release_notifier.egg-info/SOURCES.txt
github_release_notifier.egg-info/dependency_links.txt
github_release_notifier.egg-info/entry_points.txt
github_release_notifier.egg-info/requires.txt
github_release_notifier.egg-info/top_level.txt