Metadata-Version: 1.2
Name: github-release-notifier
Version: 0.4.5
Summary: Get notified when a specific package got a new release on Github
Home-page: https://github.com/femtopixel/github-release-notifier/
Author: Jay MOULIN
Author-email: jaymoulin+github-release-notifier@gmail.com
License: MIT
Platform: UNKNOWN
Classifier: Development Status :: 5 - Production/Stable
Classifier: Programming Language :: Python
Classifier: License :: OSI Approved :: MIT License
Classifier: Natural Language :: English
Classifier: Operating System :: OS Independent
Classifier: Programming Language :: Python :: 3
Classifier: Topic :: Communications
Classifier: Topic :: Internet
Classifier: Topic :: Software Development :: Pre-processors
Classifier: Intended Audience :: Developers
Classifier: Topic :: Software Development :: Build Tools
Requires-Python: >=3
